{"basics":{"name":"Zaifu Zhan","label":"Research and Teaching Assistant","image":"","email":"zhan8023@umn.edu","url":"https://learner4everrr.github.io/","summary":"Ph.D. student in Electrical and Computer Engineering at the University of Minnesota, Twin Cities","location":{"address":"","postalCode":"","city":"Minneapolis","countryCode":"US","region":"Minnesota"},"profiles":[{"network":"Twitter","username":"AlbertEinstein","url":"https://twitter.com/AlbertEinstein"}]},"education":[{"institution":"University of Minnesota, Twin Cities","location":"Minneapolis","url":"https://twin-cities.umn.edu/","area":"Electrical and Computer Engineering","studyType":"Doctor of Philosophy","startDate":"2021","endDate":"2026","score":"","courses1":["EE 5231  Lnr Sys Optml Cntrl","EE 8231  Optmztn Theory","CSCI 5525 Advanced Machine Learning","EE 5235  Robust Cntrl Sys","MATH 5652 Intro Stoch Process","EE 5241  Opt Contr & Reinfrcmnt Lrning","EE 5251  Optimal Filtering & Estimation","MATH 5615H  Honors Analysis I","MATH 5616H Honors Analysis II","EE 8215 Nonlinear Systms","CSCI 5527 Deep Learning","MATH 5711  Linear Programming","CSCI 5541 Natural Language Processing","CSCI 5609  Visualization"]},{"institution":"Tsinghua University","location":"Beijing","url":"https://www.tsinghua.edu.cn/en/","area":"Electrical Engineering","studyType":"Master of Engineering","startDate":"2018","endDate":"2021","score":"","courses":[]},{"institution":"Beijing Jiaotong University","location":"Beijing","url":"http://en.njtu.edu.cn/","area":"Electrical Engineering","studyType":"Bachelor of Science","startDate":"2014","endDate":"2018","score":"","courses":[]}],"work":[{"name":"University of Minnesota, Twin Cities","location":"Minneapolis","position":"Graduate Research Assistant","startDate":"2021-09-01","endDate":"Now","summary":"Biomedical NLP, Optimzation, Model-free control","highlights":[]},{"name":"University of Minnesota, Twin Cities","location":"Minneapolis","position":"Graduate Teaching Assistant","startDate":"2022-09-01","endDate":"Now","summary":"Hosting lab sessions and office hours","highlights":["EE 4541 Digital Signal Processing","EE 5373 Data Modeling Using R","EE 2015 Signals, Circuits and Electronics"]},{"name":"Xu’s Research Group, University of Wisconsin-Madison","location":"Remote","position":"Graduate Research Assistant","startDate":"2020-03-01","endDate":"2020-08-30","summary":"Quadrotor trajectory planning based on control barrier function","highlights":[]},{"name":"State Key Laboratory of Power System, Tsinghua University","location":"Beijing","position":"Graduate Research Assistant","startDate":"2018-09-01","endDate":"2021-07-30","summary":"Micro-crack detection using nonlinear ultrasound","highlights":[]}],"volunteer":[],"awards":[],"certificates":[],"publications":[],"skills":[],"languages":[],"interests":[],"references":[],"projects":[]}